breaching/README.md
breaching/__init__.py
breaching/utils.py
breaching/analysis/README.md
breaching/analysis/__init__.py
breaching/analysis/analysis.py
breaching/analysis/imprint_guarantee.py
breaching/analysis/metrics.py
breaching/attacks/README.md
breaching/attacks/__init__.py
breaching/attacks/analytic_attack.py
breaching/attacks/base_attack.py
breaching/attacks/multiscale_optimization_attack.py
breaching/attacks/optimization_based_attack.py
breaching/attacks/optimization_permutation_attack.py
breaching/attacks/optimization_with_label_attack.py
breaching/attacks/recursive_attack.py
breaching/attacks/auxiliaries/README.md
breaching/attacks/auxiliaries/__init__.py
breaching/attacks/auxiliaries/augmentations.py
breaching/attacks/auxiliaries/common.py
breaching/attacks/auxiliaries/conv2circulant.py
breaching/attacks/auxiliaries/deepinversion.py
breaching/attacks/auxiliaries/make_functional.py
breaching/attacks/auxiliaries/objectives.py
breaching/attacks/auxiliaries/recursive_attack.py
breaching/attacks/auxiliaries/regularizers.py
breaching/cases/README.md
breaching/cases/__init__.py
breaching/cases/servers.py
breaching/cases/users.py
breaching/cases/aux_training/VAE.py
breaching/cases/aux_training/__init__.py
breaching/cases/aux_training/nearest_embed.py
breaching/cases/data/__init__.py
breaching/cases/data/cached_dataset.py
breaching/cases/data/data_preparation.py
breaching/cases/data/datasets_text.py
breaching/cases/data/datasets_vision.py
breaching/cases/data/lmdb_datasets.py
breaching/cases/data/wordlevel_tokenizer.py
breaching/cases/malicious_modifications/__init__.py
breaching/cases/malicious_modifications/analytic_transformer_utils.py
breaching/cases/malicious_modifications/classattack_utils.py
breaching/cases/malicious_modifications/feat_decoders.py
breaching/cases/malicious_modifications/imprint.py
breaching/cases/malicious_modifications/parameter_utils.py
breaching/cases/models/__init__.py
breaching/cases/models/densenets.py
breaching-0.1.2.dist-info/LICENSE.md
breaching-0.1.2.dist-info/METADATA
breaching-0.1.2.dist-info/WHEEL
breaching-0.1.2.dist-info/top_level.txt
breaching-0.1.2.dist-info/RECORD
