Metadata-Version: 2.1
Name: breaching
Version: 0.1.2
Summary: Framework for Attacks against Privacy in Federated Learning
Home-page: https://github.com/JonasGeiping/breaching
Author: Jonas Geiping
Author-email: jonas.geiping@gmail.com
License: MIT
Keywords: Federated Learning,Privacy,PyTorch,Machine Learning,Security Audit,Research
Platform: any
Classifier: Topic :: Security
Classifier: License :: OSI Approved :: MIT License
Classifier: Operating System :: OS Independent
Classifier: Programming Language :: Python
Requires-Python: >=3.7
License-File: LICENSE.md
Requires-Dist: torch (>=1.10)
Requires-Dist: torchvision
Requires-Dist: hydra-core (>=1.1)
Requires-Dist: scipy
Requires-Dist: lpips
